kira_setup/__init__.py
kira_setup/api.py
kira_setup/cli.py
kira_setup/logging.py
kira_setup/pipelines/__init__.py
kira_setup/pipelines/labels.py
kira_setup/pipelines/merge_requests.py
kira_setup/pipelines/project.py
kira_setup/pipelines/protected.py
kira_setup-0.1.0.dist-info/entry_points.txt
kira_setup-0.1.0.dist-info/LICENSE
kira_setup-0.1.0.dist-info/WHEEL
kira_setup-0.1.0.dist-info/METADATA
kira_setup-0.1.0.dist-info/RECORD
