Metadata-Version: 2.1
Name: kira-setup
Version: 0.1.0
Summary: Kira's CLI to setup new projects
Home-page: https://github.com/wemake-services/kira-setup
License: MIT
Keywords: wemake.services,gitlab-bot,gitlab,kira,kira-bot
Author: sobolevn
Author-email: mail@sobolevn.me
Requires-Python: >=3.6,<4.0
Classifier: Development Status :: 5 - Production/Stable
Classifier: Environment :: Console
Classifier: Intended Audience :: Developers
Classifier: License :: OSI Approved :: MIT License
Classifier: Operating System :: OS Independent
Classifier: Programming Language :: Python
Classifier: Programming Language :: Python :: 3
Classifier: Programming Language :: Python :: 3.6
Classifier: Programming Language :: Python :: 3.7
Classifier: Programming Language :: Python :: Implementation :: CPython
Requires-Dist: python-gitlab (>=1.8,<2.0)
Requires-Dist: termcolor (>=1.1,<2.0)
Project-URL: Repository, https://github.com/wemake-services/kira-setup
